{"ballots":{},"categories":{"14":{"category_id":14,"name":"Best Overall","is_primary":true,"created_at":"2018-09-02T05:08:52.183Z","updated_at":"2018-09-05T01:10:42.834Z","criteria":[{"criteria_id":16,"name":"Design/Usability","rubric":"How usable is the design?\nIs it ready to ship?\nIf you had no context about the project, would you know what to do?","min_score":1,"max_score":10,"category_id":14,"created_at":"2018-09-02T05:08:52.521Z","updated_at":"2018-09-05T01:10:42.512Z"},{"criteria_id":17,"name":"Presentation","rubric":"How was the demo?\nDid everything go to plan?\nHow do you feel about the project as a whole based solely on the presentation they gave. ","min_score":1,"max_score":10,"category_id":14,"created_at":"2018-09-02T05:08:52.539Z","updated_at":"2018-09-05T01:10:42.535Z"},{"criteria_id":19,"name":"Technical Depth","rubric":"How complex is the code?\nHow much of the project depends on the backend code?\nDid the project use cool technologies?\nDid the project use all the features of a library?","min_score":1,"max_score":10,"category_id":14,"created_at":"2018-09-02T05:55:16.425Z","updated_at":"2018-09-05T01:10:42.802Z"},{"criteria_id":18,"name":"Novelty","rubric":"How novel is the idea?\nDid you already see something like this today?\nHas it been done before?\nIs this idea cute or unique?","min_score":1,"max_score":10,"category_id":14,"created_at":"2018-09-02T05:08:52.556Z","updated_at":"2018-09-05T01:10:42.808Z"}]},"15":{"category_id":15,"name":"Rube Goldberg","is_primary":false,"created_at":"2018-09-02T06:07:55.753Z","updated_at":"2018-09-07T19:58:19.814Z","criteria":[{"criteria_id":20,"name":"Task Simplicity","rubric":"How simple was the original task?","min_score":1,"max_score":10,"category_id":15,"created_at":"2018-09-02T06:07:55.966Z","updated_at":"2018-09-07T19:58:19.496Z"},{"criteria_id":21,"name":"Project Complexity","rubric":"How many steps did the project use to accomplish the task?\nThe score is subjective, not an actual defined number. ","min_score":1,"max_score":10,"category_id":15,"created_at":"2018-09-02T06:07:56.074Z","updated_at":"2018-09-07T19:58:19.790Z"},{"criteria_id":25,"name":"Overall Execution","rubric":"How well did the project accomplish the task?","min_score":1,"max_score":10,"category_id":15,"created_at":"2018-09-02T06:12:50.270Z","updated_at":"2018-09-07T19:58:19.796Z"}]},"16":{"category_id":16,"name":"Vanilla","is_primary":false,"created_at":"2018-09-02T06:09:58.085Z","updated_at":"2018-09-04T19:31:13.636Z","criteria":[{"criteria_id":22,"name":"Library Usage","rubric":"Did the project use a lot of libraries?\n1: The project used many libraries.\n10: The project used no libraries. ","min_score":1,"max_score":10,"category_id":16,"created_at":"2018-09-02T06:09:58.300Z","updated_at":"2018-09-04T19:31:13.314Z"}]},"17":{"category_id":17,"name":"Design Oriented","is_primary":false,"created_at":"2018-09-02T06:10:40.020Z","updated_at":"2018-09-04T19:31:16.315Z","criteria":[{"criteria_id":23,"name":"Overall Design Score","rubric":"Subjectively, how pretty is the project?\nHow easy is it to use?","min_score":1,"max_score":10,"category_id":17,"created_at":"2018-09-02T06:10:40.232Z","updated_at":"2018-09-04T19:31:15.962Z"}]},"18":{"category_id":18,"name":"Code Golf","is_primary":false,"created_at":"2018-09-02T06:11:58.668Z","updated_at":"2018-09-04T19:31:11.594Z","criteria":[{"criteria_id":24,"name":"Filesize","rubric":"How big is the actual project?\n1: The project is huge!\n10: The project is a couple bytes.","min_score":1,"max_score":10,"category_id":18,"created_at":"2018-09-02T06:11:58.917Z","updated_at":"2018-09-04T19:31:11.270Z"}]},"20":{"category_id":20,"name":"Best Microsoft Tech Hack","is_primary":false,"created_at":"2018-09-04T20:55:31.874Z","updated_at":"2018-09-04T20:55:38.573Z","criteria":[{"criteria_id":27,"name":"Is a Hack","rubric":"Exists","min_score":1,"max_score":10,"category_id":20,"created_at":"2018-09-04T20:55:32.075Z","updated_at":"2018-09-04T20:55:32.075Z"}]}},"criteria":{"16":{"criteria_id":16,"name":"Design/Usability","rubric":"How usable is the design?\nIs it ready to ship?\nIf you had no context about the project, would you know what to do?","min_score":1,"max_score":10,"category_id":14,"created_at":"2018-09-02T05:08:52.521Z","updated_at":"2018-09-05T01:10:42.512Z"},"17":{"criteria_id":17,"name":"Presentation","rubric":"How was the demo?\nDid everything go to plan?\nHow do you feel about the project as a whole based solely on the presentation they gave. ","min_score":1,"max_score":10,"category_id":14,"created_at":"2018-09-02T05:08:52.539Z","updated_at":"2018-09-05T01:10:42.535Z"},"18":{"criteria_id":18,"name":"Novelty","rubric":"How novel is the idea?\nDid you already see something like this today?\nHas it been done before?\nIs this idea cute or unique?","min_score":1,"max_score":10,"category_id":14,"created_at":"2018-09-02T05:08:52.556Z","updated_at":"2018-09-05T01:10:42.808Z"},"19":{"criteria_id":19,"name":"Technical Depth","rubric":"How complex is the code?\nHow much of the project depends on the backend code?\nDid the project use cool technologies?\nDid the project use all the features of a library?","min_score":1,"max_score":10,"category_id":14,"created_at":"2018-09-02T05:55:16.425Z","updated_at":"2018-09-05T01:10:42.802Z"},"20":{"criteria_id":20,"name":"Task Simplicity","rubric":"How simple was the original task?","min_score":1,"max_score":10,"category_id":15,"created_at":"2018-09-02T06:07:55.966Z","updated_at":"2018-09-07T19:58:19.496Z"},"21":{"criteria_id":21,"name":"Project Complexity","rubric":"How many steps did the project use to accomplish the task?\nThe score is subjective, not an actual defined number. ","min_score":1,"max_score":10,"category_id":15,"created_at":"2018-09-02T06:07:56.074Z","updated_at":"2018-09-07T19:58:19.790Z"},"22":{"criteria_id":22,"name":"Library Usage","rubric":"Did the project use a lot of libraries?\n1: The project used many libraries.\n10: The project used no libraries. ","min_score":1,"max_score":10,"category_id":16,"created_at":"2018-09-02T06:09:58.300Z","updated_at":"2018-09-04T19:31:13.314Z"},"23":{"criteria_id":23,"name":"Overall Design Score","rubric":"Subjectively, how pretty is the project?\nHow easy is it to use?","min_score":1,"max_score":10,"category_id":17,"created_at":"2018-09-02T06:10:40.232Z","updated_at":"2018-09-04T19:31:15.962Z"},"24":{"criteria_id":24,"name":"Filesize","rubric":"How big is the actual project?\n1: The project is huge!\n10: The project is a couple bytes.","min_score":1,"max_score":10,"category_id":18,"created_at":"2018-09-02T06:11:58.917Z","updated_at":"2018-09-04T19:31:11.270Z"},"25":{"criteria_id":25,"name":"Overall Execution","rubric":"How well did the project accomplish the task?","min_score":1,"max_score":10,"category_id":15,"created_at":"2018-09-02T06:12:50.270Z","updated_at":"2018-09-07T19:58:19.796Z"},"27":{"criteria_id":27,"name":"Is a Hack","rubric":"Exists","min_score":1,"max_score":10,"category_id":20,"created_at":"2018-09-04T20:55:32.075Z","updated_at":"2018-09-04T20:55:32.075Z"}},"projects":{},"users":{"10":{"user_id":10,"email":"jameslu1998@gmail.com","name":"James Lu","user_class":"Owner"},"11":{"user_id":11,"email":"bob@bob.com","name":"Bobby Judge","user_class":"Judge"},"12":{"user_id":12,"email":"bob@bob.net","name":"bobby","user_class":"Pending"},"13":{"user_id":13,"email":"joe@joe.com","name":"BObby","user_class":"Pending"},"14":{"user_id":14,"email":"test@test.com","name":"Test","user_class":"Judge"}},"judgeQueues":{}}